doc/contributing.md
test/conftest.py
test/test_editor_load.py
test/test_gui.py
test/data/option_d.py
viscm/__init__.py
viscm/__main__.py
viscm/cli.py
viscm/gui.py
viscm/minimvc.py
viscm/bezierbuilder/__init__.py
viscm/bezierbuilder/curve.py
viscm/examples/README
viscm/examples/colourmaptest.npy
viscm/examples/hist2d.txt
viscm/examples/sample_diverging.jscm
viscm/examples/sample_diverging_continuous.jscm
viscm/examples/sample_linear.jscm
viscm/examples/st-helens_before-modified.txt.gz
viscm-0.10.dist-info/LICENSE
viscm-0.10.dist-info/METADATA
viscm-0.10.dist-info/WHEEL
viscm-0.10.dist-info/entry_points.txt
viscm-0.10.dist-info/top_level.txt
viscm-0.10.dist-info/RECORD
