Metadata-Version: 2.1
Name: viscm
Version: 0.10
Summary: A colormap tool
Author-email: "Nathaniel J. Smith" <njs@pobox.com>, Stefan van der Walt <stefanv@berkeley.edu>
License: MIT
Project-URL: repository, https://github.com/matplotlib/viscm
Classifier: Development Status :: 3 - Alpha
Classifier: Intended Audience :: Developers
Classifier: Intended Audience :: Science/Research
Classifier: License :: OSI Approved :: MIT License
Classifier: Programming Language :: Python :: 3
Requires-Python: ~=3.9
License-File: LICENSE
Requires-Dist: numpy (~=1.22)
Requires-Dist: matplotlib (~=3.5)
Requires-Dist: colorspacious (~=1.1)
Requires-Dist: scipy (~=1.8)
Provides-Extra: pyqt
Requires-Dist: PyQt6 ; extra == 'pyqt'
Provides-Extra: pyside
Requires-Dist: PySide6 ; extra == 'pyside'
